GuiMPLpretest/__init__.py
GuiMPLpretest/app.py
GuiMPLpretest/controller.py
GuiMPLpretest/dico_params.py
GuiMPLpretest/model.py
GuiMPLpretest/view.py
GuiMPLpretest/custom_widgets/__init__.py
GuiMPLpretest/custom_widgets/color_chooser.py
GuiMPLpretest/custom_widgets/double_spinbox.py
GuiMPLpretest/row_pygubu/__init__.py
GuiMPLpretest/row_pygubu/autowidgets_base_frame.py
GuiMPLpretest/row_pygubu/axeschoosewidgetsframe.py
GuiMPLpretest/row_pygubu/axewidgetsbaseframe.py
GuiMPLpretest/row_pygubu/row_pygubu_main.py
GuiMPLpretest/surcouches_pygubu/__init__.py
GuiMPLpretest/surcouches_pygubu/autowidgetsframe.py
GuiMPLpretest/surcouches_pygubu/mainaxewidgetsframewidget.py
GuiMPLpretest-0.0.10.dist-info/METADATA
GuiMPLpretest-0.0.10.dist-info/WHEEL
GuiMPLpretest-0.0.10.dist-info/top_level.txt
GuiMPLpretest-0.0.10.dist-info/RECORD
